travis_pypi_integration/__init__.py
travis_pypi_integration-2.1.2.dist-info/LICENSE
travis_pypi_integration-2.1.2.dist-info/METADATA
travis_pypi_integration-2.1.2.dist-info/WHEEL
travis_pypi_integration-2.1.2.dist-info/top_level.txt
travis_pypi_integration-2.1.2.dist-info/RECORD
